model_perf/__init__.py
model_perf/globals.py
model_perf/logger.py
model_perf/metrics.py
model_perf/model_runner.py
model_perf/utils.py
model_perf/dataset/__init__.py
model_perf/dataset/dataset.py
model_perf/dataset/dataset_factory.py
model_perf/dataset/json_helper.py
model_perf/dataset/msgpack_helper.py
model_perf/desktop/__init__.py
model_perf/desktop/desktop_model_runner.py
model_perf/desktop/test_app.py
model_perf/lib/load_gen_c.cp39-win_amd64.pyd
model_perf/mobile/__init__.py
model_perf/mobile/appcenter_helper.py
model_perf/mobile/appcenter_model_runner.py
model_perf/mobile/appium_local_model_runner.py
model_perf/mobile/avd_model_runner.py
model_perf/mobile/mobile_model_runner.py
model_perf/mobile/performance_helper.py
model_perf/mobile/test_app.py
model_perf/model/__init__.py
model_perf/model/model_assets.py
model_perf/server/__init__.py
model_perf/server/async_worker.py
model_perf/server/server_model_runner.py
model_perf/server/sync_worker.py
model_perf/server/worker.py
model_perf/server/load_gen/__init__.py
model_perf/web/__init__.py
model_perf/web/test_app.py
model_perf/web/web_driver.py
model_perf/web/web_model_runner.py
model_perf-0.0.1rc1.dist-info/LICENSE
model_perf-0.0.1rc1.dist-info/METADATA
model_perf-0.0.1rc1.dist-info/WHEEL
model_perf-0.0.1rc1.dist-info/top_level.txt
model_perf-0.0.1rc1.dist-info/RECORD
